custom_ai/__init__.py
custom_ai/whisper.py
custom_ai-0.1.0.dist-info/METADATA
custom_ai-0.1.0.dist-info/WHEEL
custom_ai-0.1.0.dist-info/top_level.txt
custom_ai-0.1.0.dist-info/RECORD
