Metadata-Version: 2.1
Name: custom-ai
Version: 0.1.0
Summary: A Whisper transcription client for seamless audio processing.
Author: difansyah
Author-email: dickyalfansyaah@gmail.com
Classifier: Programming Language :: Python :: 3
Classifier: License :: OSI Approved :: MIT License
Classifier: Operating System :: OS Independent
Requires-Python: >=3.7
Requires-Dist: requests
